{"cameraMode":{"drawMode":0,"name":"Shaded","section":"Shading Mode"},"sceneLighting":false,"audioPlay":false,"sceneViewState":{"m_AlwaysRefresh":false,"showFog":true,"showSkybox":false,"showFlares":true,"showImageEffects":true,"showParticleSystems":true,"showVisualEffectGraphs":true,"m_FxEnabled":true},"in2DMode":false,"pivot":{"x":0.07285642623901367,"y":-0.10677146911621094,"z":24.128873825073243},"rotation":{"x":-0.16351580619812013,"y":0.6336150765419006,"z":-0.14426088333129884,"w":-0.7433873414993286},"size":29.941837310791017,"orthographic":false}